escher/__init__.py
escher/run_time.py
escher_cli/__init__.py
escher_cli/escher.py
escher_cli/escher_runner.py
escher_cli/escherd.py
escher_cli/helpers.py
escher_cli/script_runner.py
escher_cli/test_escher.py
escher_cli-0.0.3.dist-info/DESCRIPTION.rst
escher_cli-0.0.3.dist-info/METADATA
escher_cli-0.0.3.dist-info/RECORD
escher_cli-0.0.3.dist-info/WHEEL
escher_cli-0.0.3.dist-info/entry_points.txt
escher_cli-0.0.3.dist-info/metadata.json
escher_cli-0.0.3.dist-info/top_level.txt
