Metadata-Version: 2.0
Name: escher-cli
Version: 0.0.3
Summary: A command line utility that runs your command line scripts from a yaml script
Home-page: https://github.com/episodeyang/escher-cli
Author: Ge Yang
Author-email: yangge1987@gmail.com
License: UNKNOWN
Keywords: escher,escher-cli,experiment,experimentation,script runner,deep learning,machine learning
Platform: UNKNOWN
Classifier: Development Status :: 4 - Beta
Classifier: Intended Audience :: Science/Research
Classifier: Programming Language :: Python :: 3
Requires-Dist: Click
Requires-Dist: click-default-group
Requires-Dist: params-proto
Requires-Dist: pathos
Requires-Dist: pathlib
Requires-Dist: munch
Requires-Dist: ruamel.yaml
